py2cy/__init__.py
py2cy/constants.py
py2cy/invoke.py
py2cy/py_to_cy.py
py2cy-0.0.1.dist-info/LICENSE
py2cy-0.0.1.dist-info/METADATA
py2cy-0.0.1.dist-info/WHEEL
py2cy-0.0.1.dist-info/entry_points.txt
py2cy-0.0.1.dist-info/top_level.txt
py2cy-0.0.1.dist-info/RECORD
