Metadata-Version: 2.2
Name: py2cy
Version: 0.0.1
Summary: A package to convert Python code to Cython for Security and Obfuscation
Author-email: Vaira Muthu Thangavel <vairamuthu.thangavel@gmail.com>
Project-URL: Homepage, https://github.com/armeggaddon/py2cy
Project-URL: Repository, https://github.com/armeggaddon/py2cy.git
Keywords: cython,encryption,conversion,security,obfuscation,code protection,anti-reverse engineering,code integrity,cythonize,privacy,intellectual property,secure code,software protection,anti-tampering,transpiler,application security,deployment
Classifier: Programming Language :: Python :: 3
Classifier: Operating System :: OS Independent
Classifier: License :: OSI Approved :: MIT License
Requires-Python: >=3.8
License-File: LICENSE
Requires-Dist: Cython>=3.0.2
